LICENSE
MANIFEST.in
README.md
setup.py
django_sns_mobile_push_notification.egg-info/PKG-INFO
django_sns_mobile_push_notification.egg-info/SOURCES.txt
django_sns_mobile_push_notification.egg-info/dependency_links.txt
django_sns_mobile_push_notification.egg-info/requires.txt
django_sns_mobile_push_notification.egg-info/top_level.txt
sns_mobile_push_notification/__init__.py
sns_mobile_push_notification/admin.py
sns_mobile_push_notification/apps.py
sns_mobile_push_notification/client.py
sns_mobile_push_notification/models.py
sns_mobile_push_notification/tasks.py
sns_mobile_push_notification/tests.py
sns_mobile_push_notification/views.py
sns_mobile_push_notification/__pycache__/__init__.cpython-34.pyc
sns_mobile_push_notification/__pycache__/admin.cpython-34.pyc
sns_mobile_push_notification/__pycache__/client.cpython-34.pyc
sns_mobile_push_notification/__pycache__/models.cpython-34.pyc
sns_mobile_push_notification/__pycache__/tasks.cpython-34.pyc
sns_mobile_push_notification/__pycache__/tests.cpython-34.pyc
sns_mobile_push_notification/migrations/0001_initial.py
sns_mobile_push_notification/migrations/__init__.py
sns_mobile_push_notification/migrations/__pycache__/0001_initial.cpython-34.pyc
sns_mobile_push_notification/migrations/__pycache__/0002_auto_20180427_1758.cpython-34.pyc
sns_mobile_push_notification/migrations/__pycache__/0003_auto_20180427_1801.cpython-34.pyc
sns_mobile_push_notification/migrations/__pycache__/0004_device_active.cpython-34.pyc
sns_mobile_push_notification/migrations/__pycache__/__init__.cpython-34.pyc