Metadata-Version: 1.1
Name: django-sns-mobile-push-notification
Version: 0.9
Summary: Send mobile push notification to IOS and android devices using Amazon SNS.
Home-page: https://github.com/pythonicrubyist
Author: Ramtin Vaziri
Author-email: pythonicrubyist@gmail.com
License: MIT License
Platform: UNKNOWN
Classifier: Environment :: Web Environment
Classifier: Framework :: Django
Classifier: Intended Audience :: Developers
Classifier: License :: OSI Approved :: MIT License
Classifier: Operating System :: OS Independent
Classifier: Programming Language :: Python
Classifier: Programming Language :: Python :: 3
Classifier: Topic :: Internet :: WWW/HTTP
Classifier: Topic :: Internet :: WWW/HTTP :: Dynamic Content
